radtraq/__init__.py
radtraq/plotting/__init__.py
radtraq/plotting/cfad.py
radtraq/plotting/corner_reflector.py
radtraq/plotting/profile.py
radtraq/plotting/self_consistency.py
radtraq/proc/__init__.py
radtraq/proc/cloud_mask.py
radtraq/proc/noise.py
radtraq/proc/profile.py
radtraq/tests/__init__.py
radtraq/tests/pytest.ini
radtraq/tests/sample_files.py
radtraq/tests/test_plotting.py
radtraq/tests/test_proc.py
radtraq/tests/test_utils.py
radtraq/tests/baseline/test_cloud_mask.png
radtraq/tests/baseline/test_corner_reflector.png
radtraq/tests/baseline/test_plotting.png
radtraq/tests/baseline/test_self_consistency.png
radtraq/utils/__init__.py
radtraq/utils/corrections.py
radtraq/utils/dataset_utils.py
radtraq/utils/utils.py
RadTraQ-0.0.9.dist-info/LICENSE
RadTraQ-0.0.9.dist-info/METADATA
RadTraQ-0.0.9.dist-info/WHEEL
RadTraQ-0.0.9.dist-info/top_level.txt
RadTraQ-0.0.9.dist-info/RECORD
