Metadata-Version: 2.1
Name: RadTraQ
Version: 0.0.9
Summary: Python package for weather radar quality tracking
Author: Adam Theisen
Author-email: atheisen@anl.gov
License: BSD (3-clause)
License-File: LICENSE
Requires-Dist: pandas
Requires-Dist: act-atmos
Requires-Dist: numpy
Requires-Dist: scipy
Requires-Dist: xarray
Requires-Dist: matplotlib
Requires-Dist: netcdf4
Requires-Dist: pint
Requires-Dist: open-radar-data
